qapy/algebra.py
qapy/algebra_core.py
qapy/algebra_ext/__init__.py
qapy/algebra_ext/toolbox.py
qapy/api/__init__.py
qapy-0.1.7.dist-info/LICENCE
qapy-0.1.7.dist-info/METADATA
qapy-0.1.7.dist-info/WHEEL
qapy-0.1.7.dist-info/top_level.txt
qapy-0.1.7.dist-info/RECORD
