Metadata-Version: 2.1
Name: qapy
Version: 0.1.7
Summary: Python components for QA: Design your contract with the algebra. Monitor and price it with the API
Author: mattcharr
Author-email: matthieu.charrier.pro@gmail.com
Maintainer-email: mattcharr <matthieu.charrier.pro@gmail.com>
Project-URL: qapp, https://github.com/matt-charr/qa-demo/releases
Project-URL: Homepage, https://github.com/matt-charr/qa-demo
Project-URL: Issues, https://github.com/matt-charr/qa-demo/issues
Classifier: Programming Language :: Python :: 3
Classifier: Operating System :: OS Independent
Classifier: Development Status :: 5 - Production/Stable
Classifier: Intended Audience :: Customer Service
Classifier: Intended Audience :: Developers
Classifier: Intended Audience :: Education
Classifier: Intended Audience :: End Users/Desktop
Classifier: Intended Audience :: Financial and Insurance Industry
Classifier: Intended Audience :: Science/Research
Classifier: License :: Free for non-commercial use
Classifier: Topic :: Adaptive Technologies
Classifier: Topic :: Artistic Software
Classifier: Topic :: Office/Business :: Financial
Classifier: Topic :: Office/Business :: Financial :: Investment
Classifier: Topic :: Office/Business :: Financial :: Accounting
Classifier: Topic :: Scientific/Engineering
Classifier: Topic :: Scientific/Engineering :: Mathematics
Classifier: Topic :: Software Development
Classifier: Topic :: Software Development :: User Interfaces
Requires-Python: >=3.8
License-File: LICENCE
